xbus/__init__.py
xbus/file_emitter/file_emitter.py
xbus/file_emitter/__init__.py
xbus.file_emitter-0.1.2.dist-info/metadata.json
xbus.file_emitter-0.1.2.dist-info/METADATA
xbus.file_emitter-0.1.2.dist-info/WHEEL
xbus.file_emitter-0.1.2.dist-info/top_level.txt
xbus.file_emitter-0.1.2.dist-info/DESCRIPTION.rst
xbus.file_emitter-0.1.2.dist-info/RECORD
