Metadata-Version: 2.0
Name: xbus.file-emitter
Version: 0.1.2
Summary: Generic Xbus file emitter.
Home-page: http://xbus.io
Author: XCG
Author-email: contact@xcg-consulting.fr
License: UNKNOWN
Keywords: xbus file emitter
Platform: UNKNOWN
Classifier: Programming Language :: Python
Classifier: Intended Audience :: Developers
Classifier: Intended Audience :: Financial and Insurance Industry
Classifier: Intended Audience :: Information Technology
Classifier: Intended Audience :: Other Audience
Classifier: Intended Audience :: Science/Research
Classifier: Intended Audience :: System Administrators
Classifier: License :: OSI Approved :: MIT License
Classifier: Operating System :: OS Independent
Classifier: Programming Language :: Python :: 3.4
Requires-Dist: msgpack-python
Requires-Dist: pyjon.descriptors
Requires-Dist: pyzmq
